AUTHORS.rst
CHANGES.rst
LICENSE.txt
MANIFEST.in
README.rst
setup.py
django_fernet_fields.egg-info/PKG-INFO
django_fernet_fields.egg-info/SOURCES.txt
django_fernet_fields.egg-info/dependency_links.txt
django_fernet_fields.egg-info/not-zip-safe
django_fernet_fields.egg-info/requires.txt
django_fernet_fields.egg-info/top_level.txt
fernet_fields/__init__.py
fernet_fields/fields.py
fernet_fields/hkdf.py
fernet_fields/models.py
fernet_fields/queryset.py
fernet_fields/test/__init__.py
fernet_fields/test/models.py
fernet_fields/test/test_fields.py
fernet_fields/test/settings/__init__.py
fernet_fields/test/settings/base.py
fernet_fields/test/settings/pg.py
fernet_fields/test/settings/sqlite.py
fernet_fields/test/testmigrate/__init__.py
fernet_fields/test/testmigrate/models.py
fernet_fields/test/testmigrate/migrations/0001_initial.py
fernet_fields/test/testmigrate/migrations/0002_add_values.py
fernet_fields/test/testmigrate/migrations/0003_add_value_dual.py
fernet_fields/test/testmigrate/migrations/0004_copy_values.py
fernet_fields/test/testmigrate/migrations/0005_remove_old_value_field.py
fernet_fields/test/testmigrate/migrations/0006_rename_value_dual.py
fernet_fields/test/testmigrate/migrations/__init__.py